README.md
setup.cfg
setup.py
pinecone/__init__.py
pinecone/client.py
pinecone_io.egg-info/PKG-INFO
pinecone_io.egg-info/SOURCES.txt
pinecone_io.egg-info/dependency_links.txt
pinecone_io.egg-info/top_level.txt