Metadata-Version: 2.1
Name: pinecone-io
Version: 0.0.1
Summary: Pinecone client libraries
Home-page: UNKNOWN
License: UNKNOWN
Platform: UNKNOWN
Classifier: Programming Language :: Python :: 3
Classifier: Topic :: Scientific/Engineering :: Artificial Intelligence
Requires-Python: >=3.6
